jiwer/__init__.py
jiwer/alignment.py
jiwer/cli.py
jiwer/measures.py
jiwer/process.py
jiwer/py.typed
jiwer/transformations.py
jiwer/transforms.py
jiwer_gml-4.0.1.dist-info/METADATA
jiwer_gml-4.0.1.dist-info/WHEEL
jiwer_gml-4.0.1.dist-info/entry_points.txt
jiwer_gml-4.0.1.dist-info/licenses/LICENSE
jiwer_gml-4.0.1.dist-info/RECORD
