Metadata-Version: 2.4
Name: jiwer-gml
Version: 4.0.1
Summary: Evaluate your speech-to-text system with similarity measures such as word error rate (WER)
Author-email: Nik Vaessen <nikvaes@gmail.com>
License-Expression: Apache-2.0
License-File: LICENSE
Requires-Python: >=3.8
Requires-Dist: click>=8.1.8
Requires-Dist: rapidfuzz>=3.9.7
